MANIFEST.in
README.md
setup.py
mxm.midifile.egg-info/PKG-INFO
mxm.midifile.egg-info/SOURCES.txt
mxm.midifile.egg-info/dependency_links.txt
mxm.midifile.egg-info/top_level.txt
mxm/midifile/__init__.py
mxm/midifile/docs/readme.md
mxm/midifile/examples/__init__.py
mxm/midifile/examples/example_print_events.py
mxm/midifile/examples/example_print_file.py
mxm/midifile/examples/example_transpose_octave.py
mxm/midifile/examples/mxm_midifile_type_0_8ch_random.py
mxm/midifile/examples/mxm_midifile_type_0_minimal.py
mxm/midifile/examples/mxm_midifile_type_1_8ch_8trk_random.py
mxm/midifile/examples/mxm_midifile_type_1_minimal.py
mxm/midifile/examples/midi-in/bach_847.mid
mxm/midifile/examples/midi-in/cubase-minimal-type1.mid
mxm/midifile/examples/midi-out/cubase-minimal-type1-transposed.mid
mxm/midifile/examples/midi-out/mxm_midifile_type_0_8ch_random.mid
mxm/midifile/examples/midi-out/mxm_midifile_type_0_minimal.mid
mxm/midifile/examples/midi-out/mxm_midifile_type_1_8ch_8trk_random.mid
mxm/midifile/examples/midi-out/mxm_midifile_type_1_minimal.mid
mxm/midifile/src/__init__.py
mxm/midifile/src/constants.py
mxm/midifile/src/data_type_converters.py
mxm/midifile/src/event_dispatcher.py
mxm/midifile/src/helpers.py
mxm/midifile/src/midi_events.py
mxm/midifile/src/midi_file_parser.py
mxm/midifile/src/midi_infile.py
mxm/midifile/src/midi_outfile.py
mxm/midifile/src/midi_to_code.py
mxm/midifile/src/raw_instream_file.py
mxm/midifile/src/raw_outstream_file.py
mxm/midifile/tests/__init__.py
mxm/midifile/tests/test_docstrings.py
mxm/midifile/tests/test_midi_files.py
mxm/midifile/tests/midifiles/ableton-glissando.mid
mxm/midifile/tests/midifiles/ableton-minimal-1note.mid
mxm/midifile/tests/midifiles/cubase-minimal-type0.mid
mxm/midifile/tests/midifiles/cubase-minimal-type1.mid
mxm/midifile/tests/midifiles/minimal.mid
mxm/midifile/tests/midifiles/readme.md