Metadata-Version: 1.1
Name: mxm.midifile
Version: 1.1
Summary: A python 3 library for reading, writing and modifying midi files
Home-page: https://github.com/maxmcorp/mxm.midifile
Author: Max M Rasmussen
Author-email: maxm@mxm.dk
License: MIT License
Keywords: midi,music,algorithmic composition,midi parser,midi reader
Platform: UNKNOWN
Classifier: Development Status :: 5 - Production/Stable
Classifier: Intended Audience :: Developers
Classifier: License :: OSI Approved :: MIT License
Classifier: Operating System :: Unix
Classifier: Operating System :: POSIX
Classifier: Operating System :: Microsoft :: Windows
Classifier: Programming Language :: Python
Classifier: Programming Language :: Python :: 3.3
Classifier: Programming Language :: Python :: 3.4
Classifier: Programming Language :: Python :: 3.5
Classifier: Programming Language :: Python :: 3.6
Classifier: Programming Language :: Python :: Implementation :: CPython
Classifier: Topic :: Artistic Software
